bulk_grades/__init__.py
bulk_grades/api.py
bulk_grades/apps.py
bulk_grades/clients.py
bulk_grades/models.py
bulk_grades/urls.py
bulk_grades/views.py
bulk_grades/migrations/0001_initial.py
bulk_grades/migrations/0002_auto_20190703_1526.py
bulk_grades/migrations/__init__.py
bulk_grades/settings/__init__.py
bulk_grades/settings/common.py
bulk_grades/settings/production.py
bulk_grades/settings/test.py
bulk_grades/templates/bulk_grades/base.html
edx_bulk_grades-1.2.0.dist-info/licenses/LICENSE.txt
edx_bulk_grades-1.2.0.dist-info/METADATA
edx_bulk_grades-1.2.0.dist-info/WHEEL
edx_bulk_grades-1.2.0.dist-info/entry_points.txt
edx_bulk_grades-1.2.0.dist-info/top_level.txt
edx_bulk_grades-1.2.0.dist-info/RECORD
